promabbix/__init__.py
promabbix/_version.py
promabbix/promabbix.py
promabbix/cli/__init__.py
promabbix/cli/generate_template.py
promabbix/core/__init__.py
promabbix/core/data_utils.py
promabbix/core/fs_utils.py
promabbix/core/migration.py
promabbix/core/template.py
promabbix/core/validation.py
promabbix/schemas/unified.yaml
promabbix/templates/prometheus_alert_rules_to_zbx_template.j2
promabbix-0.1.0.dist-info/licenses/LICENSE.md
promabbix-0.1.0.dist-info/METADATA
promabbix-0.1.0.dist-info/WHEEL
promabbix-0.1.0.dist-info/entry_points.txt
promabbix-0.1.0.dist-info/top_level.txt
promabbix-0.1.0.dist-info/RECORD
