Metadata-Version: 2.4
Name: promabbix
Version: 0.1.0
Summary: Tool for connecting Prometheus to Zabbix monitoring
Author-email: "Wrike Inc." <david.pech@team.wrike.com>
Maintainer-email: "Wrike Inc." <david.pech@team.wrike.com>
License: MIT
Project-URL: Homepage, https://github.com/wrike/promabbix
Project-URL: Repository, https://github.com/wrike/promabbix.git
Project-URL: Issues, https://github.com/wrike/promabbix/issues
Project-URL: Documentation, https://github.com/wrike/promabbix#readme
Keywords: prometheus,zabbix,monitoring,alerting,devops
Classifier: Development Status :: 5 - Production/Stable
Classifier: Intended Audience :: Developers
Classifier: Intended Audience :: System Administrators
Classifier: License :: OSI Approved :: MIT License
Classifier: Operating System :: OS Independent
Classifier: Programming Language :: Python :: 3
Classifier: Programming Language :: Python :: 3.11
Classifier: Programming Language :: Python :: 3.12
Classifier: Topic :: System :: Monitoring
Classifier: Topic :: System :: Systems Administration
Classifier: Environment :: Console
Requires-Python: >=3.11
License-File: LICENSE.md
Requires-Dist: ansible-core==2.17.*
Requires-Dist: attrs==23.2.0
Requires-Dist: click==8.1.*
Requires-Dist: pydantic==2.8.*
Requires-Dist: Jinja2==3.1.*
Requires-Dist: PyYAML==6.0.*
Requires-Dist: rich==14.0.*
Provides-Extra: dev
Requires-Dist: pytest>=7.0; extra == "dev"
Requires-Dist: pytest-cov>=4.0; extra == "dev"
Requires-Dist: pytest-mock>=3.0; extra == "dev"
Requires-Dist: flake8>=6.0; extra == "dev"
Requires-Dist: mypy>=1.0; extra == "dev"
Dynamic: license-file
